{"metadata": {"dbt_schema_version": "https://schemas.getdbt.com/dbt/run-results/v6.json", "dbt_version": "1.11.7", "generated_at": "2026-06-22T20:20:19.941904Z", "invocation_id": "9d626254-1131-4f5a-9f00-ad8938af65d3", "invocation_started_at": "2026-06-22T20:20:10.566536Z", "env": {}}, "results": [{"status": "success", "timing": [{"name": "compile", "started_at": "2026-06-22T20:20:17.260963Z", "completed_at": "2026-06-22T20:20:17.270581Z"}, {"name": "execute", "started_at": "2026-06-22T20:20:17.271826Z", "completed_at": "2026-06-22T20:20:17.271833Z"}], "thread_id": "Thread-5 (worker)", "execution_time": 0.02118396759033203, "adapter_response": {}, "message": null, "failures": null, "unique_id": "operation.airbnb.airbnb-on-run-start-0", "compiled": true, "compiled_code": "CREATE TABLE IF NOT EXISTS PROD.audit_log ( model_name STRING, run_timestamp TIMESTAMP )", "relation_name": null, "batch_results": null}, {"status": "success", "timing": [{"name": "compile", "started_at": "2026-06-22T20:20:17.273444Z", "completed_at": "2026-06-22T20:20:17.274846Z"}, {"name": "execute", "started_at": "2026-06-22T20:20:17.277528Z", "completed_at": "2026-06-22T20:20:17.277534Z"}], "thread_id": "Thread-3 (worker)", "execution_time": 0.006354808807373047, "adapter_response": {}, "message": null, "failures": null, "unique_id": "seed.airbnb.seed_full_moon_dates", "compiled": null, "compiled_code": null, "relation_name": null, "batch_results": null}, {"status": "success", "timing": [{"name": "compile", "started_at": "2026-06-22T20:20:17.275579Z", "completed_at": "2026-06-22T20:20:17.277270Z"}, {"name": "execute", "started_at": "2026-06-22T20:20:17.280310Z", "completed_at": "2026-06-22T20:20:17.280314Z"}], "thread_id": "Thread-2 (worker)", "execution_time": 0.008114099502563477, "adapter_response": {}, "message": null, "failures": null, "unique_id": "snapshot.airbnb.scd_raw_hosts", "compiled": true, "compiled_code": "select * from AIRBNB.raw.raw_hosts", "relation_name": "AIRBNB.PROD.scd_raw_hosts", "batch_results": null}, {"status": "success", "timing": [{"name": "compile", "started_at": "2026-06-22T20:20:17.277925Z", "completed_at": "2026-06-22T20:20:17.279839Z"}, {"name": "execute", "started_at": "2026-06-22T20:20:17.280949Z", "completed_at": "2026-06-22T20:20:17.280953Z"}], "thread_id": "Thread-4 (worker)", "execution_time": 0.008276939392089844, "adapter_response": {}, "message": null, "failures": null, "unique_id": "snapshot.airbnb.scd_raw_listings", "compiled": true, "compiled_code": "select * from AIRBNB.raw.raw_listings", "relation_name": "AIRBNB.PROD.scd_raw_listings", "batch_results": null}, {"status": "success", "timing": [{"name": "compile", "started_at": "2026-06-22T20:20:17.281304Z", "completed_at": "2026-06-22T20:20:17.293080Z"}, {"name": "execute", "started_at": "2026-06-22T20:20:17.296148Z", "completed_at": "2026-06-22T20:20:17.296153Z"}], "thread_id": "Thread-5 (worker)", "execution_time": 0.02086782455444336, "adapter_response": {}, "message": null, "failures": null, "unique_id": "test.airbnb.dbt_expectations_source_expect_column_distinct_count_to_equal_airbnb_listings_room_type__4.1e56c20a65", "compiled": true, "compiled_code": "\n\n\n    with grouped_expression as (\n    select\n        \n        \n    \n  \ncount(distinct room_type) = 4\n as expression\n\n\n    from AIRBNB.raw.raw_listings\n    \n\n),\nvalidation_errors as (\n\n    select\n        *\n    from\n        grouped_expression\n    where\n        not(expression = true)\n\n)\n\nselect *\nfrom validation_errors\n\n\n", "relation_name": "AIRBNB.DBT_TEST__AUDIT.dbt_expectations_source_expect_d9770018e28873e7be74335902d9e4e5", "batch_results": null}, {"status": "success", "timing": [{"name": "compile", "started_at": "2026-06-22T20:20:17.285694Z", "completed_at": "2026-06-22T20:20:17.296530Z"}, {"name": "execute", "started_at": "2026-06-22T20:20:17.296999Z", "completed_at": "2026-06-22T20:20:17.297002Z"}], "thread_id": "Thread-3 (worker)", "execution_time": 0.012758016586303711, "adapter_response": {}, "message": null, "failures": null, "unique_id": "test.airbnb.dbt_expectations_source_expect_column_values_to_match_regex_airbnb_listings_price___0_9_0_9_.09375076a9", "compiled": true, "compiled_code": "\n\n\n\n\n    with grouped_expression as (\n    select\n        \n        \n    \n  \n\n\n    \nregexp_instr(price, '^\\\\$[0-9][0-9\\\\.]+$', 1, 1, 0, '')\n\n\n > 0\n as expression\n\n\n    from AIRBNB.raw.raw_listings\n    \n\n),\nvalidation_errors as (\n\n    select\n        *\n    from\n        grouped_expression\n    where\n        not(expression = true)\n\n)\n\nselect *\nfrom validation_errors\n\n\n\n\n", "relation_name": "AIRBNB.DBT_TEST__AUDIT.dbt_expectations_source_expect_a60b59a84fbc4577a11df360c50013bb", "batch_results": null}, {"status": "success", "timing": [{"name": "compile", "started_at": "2026-06-22T20:20:17.288969Z", "completed_at": "2026-06-22T20:20:17.297353Z"}, {"name": "execute", "started_at": "2026-06-22T20:20:17.298121Z", "completed_at": "2026-06-22T20:20:17.298124Z"}], "thread_id": "Thread-2 (worker)", "execution_time": 0.01336526870727539, "adapter_response": {}, "message": null, "failures": null, "unique_id": "model.airbnb.dim_listings_cleansed", "compiled": true, "compiled_code": "\nWITH  __dbt__cte__src_listings as (\nWITH raw_listings AS (\n    SELECT\n        *\n    FROM\n        AIRBNB.raw.raw_listings\n)\nSELECT\n    id AS listing_id,\n    name AS listing_name,\n    listing_url,\n    room_type,\n    minimum_nights,\n    host_id,\n    price AS price_str,\n    created_at,\n    updated_at\nFROM\n    raw_listings\n), src_listings AS (\n  SELECT\n    *\n  FROM\n    __dbt__cte__src_listings\n)\nSELECT\n  listing_id,\n  listing_name,\n  room_type,\n  CASE\n    WHEN minimum_nights = 0 THEN 1\n    ELSE minimum_nights\n  END AS minimum_nights,\n  host_id,\n  REPLACE(\n    price_str,\n    '$'\n  ) :: NUMBER(\n    10,\n    2\n  ) AS price,\n  created_at,\n  updated_at\nFROM\n  src_listings", "relation_name": "AIRBNB.PROD.dim_listings_cleansed", "batch_results": null}, {"status": "success", "timing": [{"name": "compile", "started_at": "2026-06-22T20:20:17.293335Z", "completed_at": "2026-06-22T20:20:17.297737Z"}, {"name": "execute", "started_at": "2026-06-22T20:20:17.298597Z", "completed_at": "2026-06-22T20:20:17.298600Z"}], "thread_id": "Thread-4 (worker)", "execution_time": 0.013345956802368164, "adapter_response": {}, "message": null, "failures": null, "unique_id": "model.airbnb.dim_hosts_cleansed", "compiled": true, "compiled_code": "\nWITH  __dbt__cte__src_hosts as (\nWITH raw_hosts AS (\n    SELECT  *\n    FROM AIRBNB.raw.raw_hosts\n)\nselect \n  id AS host_id,\n  name AS host_name,\n  is_superhost,\n  created_at,\n  updated_at\nfrom raw_hosts\n), src_hosts AS (\n  SELECT\n    *\n  FROM\n    __dbt__cte__src_hosts\n)\nselect \n  host_id,\n  NVL(host_name, 'Anonymous') AS host_name,\n  is_superhost,\n  created_at,\n  updated_at\n  from src_hosts", "relation_name": "AIRBNB.PROD.dim_hosts_cleansed", "batch_results": null}, {"status": "success", "timing": [{"name": "compile", "started_at": "2026-06-22T20:20:17.301225Z", "completed_at": "2026-06-22T20:20:17.327513Z"}, {"name": "execute", "started_at": "2026-06-22T20:20:17.327713Z", "completed_at": "2026-06-22T20:20:17.327725Z"}], "thread_id": "Thread-5 (worker)", "execution_time": 0.030253171920776367, "adapter_response": {}, "message": null, "failures": null, "unique_id": "model.airbnb.fct_reviews", "compiled": true, "compiled_code": "\nWITH  __dbt__cte__src_reviews as (\nWITH raw_reviews AS (\n    SELECT\n        *\n    FROM\n        AIRBNB.raw.raw_reviews\n)\nSELECT\n    listing_id,\n    date AS review_date,\n    reviewer_name,\n    comments AS review_text,\n    sentiment AS review_sentiment  \nFROM raw_reviews\n), src_reviews AS (\n  SELECT * FROM __dbt__cte__src_reviews\n)\nSELECT\n  md5(cast(coalesce(cast(listing_id as TEXT), '_dbt_utils_surrogate_key_null_') || '-' || coalesce(cast(review_date as TEXT), '_dbt_utils_surrogate_key_null_') || '-' || coalesce(cast(reviewer_name as TEXT), '_dbt_utils_surrogate_key_null_') || '-' || coalesce(cast(review_text as TEXT), '_dbt_utils_surrogate_key_null_') as TEXT)) as review_id,\n  *\nFROM src_reviews\nWHERE review_text is not null\n\n\n  \n    AND review_date > (select max(review_date) from AIRBNB.PROD.fct_reviews)\n    \n  \n", "relation_name": "AIRBNB.PROD.fct_reviews", "batch_results": null}, {"status": "success", "timing": [{"name": "compile", "started_at": "2026-06-22T20:20:17.310319Z", "completed_at": "2026-06-22T20:20:17.330105Z"}, {"name": "execute", "started_at": "2026-06-22T20:20:17.330461Z", "completed_at": "2026-06-22T20:20:17.330467Z"}], "thread_id": "Thread-3 (worker)", "execution_time": 0.03163599967956543, "adapter_response": {}, "message": null, "failures": null, "unique_id": "model.airbnb.dim_fullmoon", "compiled": true, "compiled_code": "import holidays\n\ndef is_holiday(date_col):\n    german_holidays = holidays.Germany()\n    is_holiday = (date_col in german_holidays)\n    return is_holiday\n\ndef model(dbt, session):\n    dbt.config(\n        materialized = \"table\",\n        packages = [\"holidays\"]\n    )\n\n    orders_df = dbt.ref(\"seed_full_moon_dates\")\n\n    df = orders_df.to_pandas()\n\n    df[\"IS_HOLIDAY\"] = df[\"FULL_MOON_DATE\"].apply(is_holiday)\n\n    # return final dataset (Pandas DataFrame)\n    return df\n\n\n# This part is user provided model code\n# you will need to copy the next section to run the code\n# COMMAND ----------\n# this part is dbt logic for get ref work, do not modify\n\ndef ref(*args, **kwargs):\n    refs = {\"seed_full_moon_dates\": \"AIRBNB.PROD.seed_full_moon_dates\"}\n    key = '.'.join(args)\n    version = kwargs.get(\"v\") or kwargs.get(\"version\")\n    if version:\n        key += f\".v{version}\"\n    dbt_load_df_function = kwargs.get(\"dbt_load_df_function\")\n    return dbt_load_df_function(refs[key])\n\n\ndef source(*args, dbt_load_df_function):\n    sources = {}\n    key = '.'.join(args)\n    return dbt_load_df_function(sources[key])\n\n\nconfig_dict = {}\nmeta_dict = {}\n\n\nclass config:\n    def __init__(self, *args, **kwargs):\n        pass\n\n    @staticmethod\n    def get(key, default=None):\n        return config_dict.get(key, default)\n\n    @staticmethod\n    def meta_get(key, default=None):\n        return meta_dict.get(key, default)\n\nclass this:\n    \"\"\"dbt.this() or dbt.this.identifier\"\"\"\n    database = \"AIRBNB\"\n    schema = \"PROD\"\n    identifier = \"dim_fullmoon\"\n    \n    def __repr__(self):\n        return 'AIRBNB.PROD.dim_fullmoon'\n\n\nclass dbtObj:\n    def __init__(self, load_df_function) -> None:\n        self.source = lambda *args: source(*args, dbt_load_df_function=load_df_function)\n        self.ref = lambda *args, **kwargs: ref(*args, **kwargs, dbt_load_df_function=load_df_function)\n        self.config = config\n        self.this = this()\n        self.is_incremental = False\n\n# COMMAND ----------\n\n\n", "relation_name": "AIRBNB.PROD.dim_fullmoon", "batch_results": null}, {"status": "success", "timing": [{"name": "compile", "started_at": "2026-06-22T20:20:17.324761Z", "completed_at": "2026-06-22T20:20:17.334173Z"}, {"name": "execute", "started_at": "2026-06-22T20:20:17.334410Z", "completed_at": "2026-06-22T20:20:17.334416Z"}], "thread_id": "Thread-4 (worker)", "execution_time": 0.024361133575439453, "adapter_response": {}, "message": null, "failures": null, "unique_id": "test.airbnb.accepted_values_dim_listings_cleansed_room_type__Entire_home_apt__Private_room__Shared_room__Hotel_room.a95127e3af", "compiled": true, "compiled_code": "\n    \n    \n\nwith all_values as (\n\n    select\n        room_type as value_field,\n        count(*) as n_records\n\n    from AIRBNB.PROD.dim_listings_cleansed\n    group by room_type\n\n)\n\nselect *\nfrom all_values\nwhere value_field not in (\n    'Entire home/apt','Private room','Shared room','Hotel room'\n)\n\n\n", "relation_name": "AIRBNB.DBT_TEST__AUDIT.accepted_values_dim_listings_c_1ca6148a08c62a5218f2a162f9d2a9a6", "batch_results": null}, {"status": "success", "timing": [{"name": "compile", "started_at": "2026-06-22T20:20:17.328597Z", "completed_at": "2026-06-22T20:20:17.335418Z"}, {"name": "execute", "started_at": "2026-06-22T20:20:17.340873Z", "completed_at": "2026-06-22T20:20:17.340879Z"}], "thread_id": "Thread-5 (worker)", "execution_time": 0.01269984245300293, "adapter_response": {}, "message": null, "failures": null, "unique_id": "test.airbnb.dim_listings_minimum_nights", "compiled": true, "compiled_code": "SELECT\n    *\nFROM\n    AIRBNB.PROD.dim_listings_cleansed\nWHERE minimum_nights < 1\nLIMIT 10", "relation_name": "AIRBNB.DBT_TEST__AUDIT.dim_listings_minimum_nights", "batch_results": null}, {"status": "success", "timing": [{"name": "compile", "started_at": "2026-06-22T20:20:17.322464Z", "completed_at": "2026-06-22T20:20:17.335592Z"}, {"name": "execute", "started_at": "2026-06-22T20:20:17.341242Z", "completed_at": "2026-06-22T20:20:17.341245Z"}], "thread_id": "Thread-2 (worker)", "execution_time": 0.03491997718811035, "adapter_response": {}, "message": null, "failures": null, "unique_id": "model.airbnb.dim_long_term_listings", "compiled": true, "compiled_code": "def model(dbt, session):\n    listings = dbt.ref(\"dim_listings_cleansed\")\n\n    return (listings.filter(listings[\"MINIMUM_NIGHTS\"] >= 30)\n                   .select(\"LISTING_ID\", \"LISTING_NAME\", \"PRICE\"))\n\n\n# This part is user provided model code\n# you will need to copy the next section to run the code\n# COMMAND ----------\n# this part is dbt logic for get ref work, do not modify\n\ndef ref(*args, **kwargs):\n    refs = {\"dim_listings_cleansed\": \"AIRBNB.PROD.dim_listings_cleansed\"}\n    key = '.'.join(args)\n    version = kwargs.get(\"v\") or kwargs.get(\"version\")\n    if version:\n        key += f\".v{version}\"\n    dbt_load_df_function = kwargs.get(\"dbt_load_df_function\")\n    return dbt_load_df_function(refs[key])\n\n\ndef source(*args, dbt_load_df_function):\n    sources = {}\n    key = '.'.join(args)\n    return dbt_load_df_function(sources[key])\n\n\nconfig_dict = {}\nmeta_dict = {}\n\n\nclass config:\n    def __init__(self, *args, **kwargs):\n        pass\n\n    @staticmethod\n    def get(key, default=None):\n        return config_dict.get(key, default)\n\n    @staticmethod\n    def meta_get(key, default=None):\n        return meta_dict.get(key, default)\n\nclass this:\n    \"\"\"dbt.this() or dbt.this.identifier\"\"\"\n    database = \"AIRBNB\"\n    schema = \"PROD\"\n    identifier = \"dim_long_term_listings\"\n    \n    def __repr__(self):\n        return 'AIRBNB.PROD.dim_long_term_listings'\n\n\nclass dbtObj:\n    def __init__(self, load_df_function) -> None:\n        self.source = lambda *args: source(*args, dbt_load_df_function=load_df_function)\n        self.ref = lambda *args, **kwargs: ref(*args, **kwargs, dbt_load_df_function=load_df_function)\n        self.config = config\n        self.this = this()\n        self.is_incremental = False\n\n# COMMAND ----------\n\n\n", "relation_name": "AIRBNB.PROD.dim_long_term_listings", "batch_results": null}, {"status": "success", "timing": [{"name": "compile", "started_at": "2026-06-22T20:20:17.331612Z", "completed_at": "2026-06-22T20:20:17.340563Z"}, {"name": "execute", "started_at": "2026-06-22T20:20:17.341626Z", "completed_at": "2026-06-22T20:20:17.341629Z"}], "thread_id": "Thread-3 (worker)", "execution_time": 0.010648012161254883, "adapter_response": {}, "message": null, "failures": null, "unique_id": "test.airbnb.minimum_row_count_dim_listings_cleansed_1000.63baeac822", "compiled": true, "compiled_code": "\nSELECT \n   COUNT(*) as cnt\nFROM \n   AIRBNB.PROD.dim_listings_cleansed \nHAVING \n    COUNT(*) < 1000 \n", "relation_name": "AIRBNB.DBT_TEST__AUDIT.minimum_row_count_dim_listings_cleansed_1000", "batch_results": null}, {"status": "success", "timing": [{"name": "compile", "started_at": "2026-06-22T20:20:17.335753Z", "completed_at": "2026-06-22T20:20:17.342957Z"}, {"name": "execute", "started_at": "2026-06-22T20:20:17.343875Z", "completed_at": "2026-06-22T20:20:17.343879Z"}], "thread_id": "Thread-4 (worker)", "execution_time": 0.008907079696655273, "adapter_response": {}, "message": null, "failures": null, "unique_id": "test.airbnb.not_null_dim_listings_cleansed_host_id.084e4105be", "compiled": true, "compiled_code": "\n    \n    \n\n\n\nselect *\nfrom AIRBNB.PROD.dim_listings_cleansed\nwhere host_id is null\n\n\n", "relation_name": "AIRBNB.DBT_TEST__AUDIT.not_null_dim_listings_cleansed_host_id", "batch_results": null}, {"status": "success", "timing": [{"name": "compile", "started_at": "2026-06-22T20:20:17.347028Z", "completed_at": "2026-06-22T20:20:17.354926Z"}, {"name": "execute", "started_at": "2026-06-22T20:20:17.355111Z", "completed_at": "2026-06-22T20:20:17.355115Z"}], "thread_id": "Thread-2 (worker)", "execution_time": 0.012012004852294922, "adapter_response": {}, "message": null, "failures": null, "unique_id": "test.airbnb.positive_values_dim_listings_cleansed_minimum_nights.5dac2ba3aa", "compiled": true, "compiled_code": "\nSELECT * FROM AIRBNB.PROD.dim_listings_cleansed WHERE minimum_nights <= 0\n", "relation_name": "AIRBNB.DBT_TEST__AUDIT.positive_values_dim_listings_cleansed_minimum_nights", "batch_results": null}, {"status": "success", "timing": [{"name": "compile", "started_at": "2026-06-22T20:20:17.344554Z", "completed_at": "2026-06-22T20:20:17.358231Z"}, {"name": "execute", "started_at": "2026-06-22T20:20:17.358841Z", "completed_at": "2026-06-22T20:20:17.358844Z"}], "thread_id": "Thread-5 (worker)", "execution_time": 0.016172170639038086, "adapter_response": {}, "message": null, "failures": null, "unique_id": "test.airbnb.not_null_dim_listings_cleansed_listing_id.2da437bec9", "compiled": true, "compiled_code": "\n    \n    \n\n\n\nselect *\nfrom AIRBNB.PROD.dim_listings_cleansed\nwhere listing_id is null\n\n\n", "relation_name": "AIRBNB.DBT_TEST__AUDIT.not_null_dim_listings_cleansed_listing_id", "batch_results": null}, {"status": "success", "timing": [{"name": "compile", "started_at": "2026-06-22T20:20:17.349193Z", "completed_at": "2026-06-22T20:20:17.358449Z"}, {"name": "execute", "started_at": "2026-06-22T20:20:17.359173Z", "completed_at": "2026-06-22T20:20:17.359180Z"}], "thread_id": "Thread-3 (worker)", "execution_time": 0.015791893005371094, "adapter_response": {}, "message": null, "failures": null, "unique_id": "test.airbnb.unique_dim_listings_cleansed_listing_id.930e4e859e", "compiled": true, "compiled_code": "\n    \n    \n\nselect\n    listing_id as unique_field,\n    count(*) as n_records\n\nfrom AIRBNB.PROD.dim_listings_cleansed\nwhere listing_id is not null\ngroup by listing_id\nhaving count(*) > 1\n\n\n", "relation_name": "AIRBNB.DBT_TEST__AUDIT.unique_dim_listings_cleansed_listing_id", "batch_results": null}, {"status": "success", "timing": [{"name": "compile", "started_at": "2026-06-22T20:20:17.352925Z", "completed_at": "2026-06-22T20:20:17.358645Z"}, {"name": "execute", "started_at": "2026-06-22T20:20:17.359634Z", "completed_at": "2026-06-22T20:20:17.359637Z"}], "thread_id": "Thread-4 (worker)", "execution_time": 0.007344245910644531, "adapter_response": {}, "message": null, "failures": null, "unique_id": "model.airbnb.dim_listings_w_hosts", "compiled": true, "compiled_code": "WITH\nl AS (\n    SELECT\n        *\n    FROM\n        AIRBNB.PROD.dim_listings_cleansed\n),\nh AS (\n    SELECT *\n    FROM AIRBNB.PROD.dim_hosts_cleansed\n)\n\nSELECT\n    l.listing_id,\n    l.listing_name,\n    l.room_type,\n    l.minimum_nights,\n    l.price,\n    l.host_id,\n    h.host_name,\n    h.is_superhost as host_is_superhost,\n    l.created_at,\n    GREATEST(l.updated_at, h.updated_at) as updated_at\nFROM l\nLEFT JOIN h ON (h.host_id = l.host_id)", "relation_name": "AIRBNB.PROD.dim_listings_w_hosts", "batch_results": null}, {"status": "success", "timing": [{"name": "compile", "started_at": "2026-06-22T20:20:17.355920Z", "completed_at": "2026-06-22T20:20:17.359462Z"}, {"name": "execute", "started_at": "2026-06-22T20:20:17.360301Z", "completed_at": "2026-06-22T20:20:17.360304Z"}], "thread_id": "Thread-2 (worker)", "execution_time": 0.0047490596771240234, "adapter_response": {}, "message": null, "failures": null, "unique_id": "test.airbnb.accepted_values_dim_hosts_cleansed_is_superhost__t__f.d6051554e4", "compiled": true, "compiled_code": "\n    \n    \n\nwith all_values as (\n\n    select\n        is_superhost as value_field,\n        count(*) as n_records\n\n    from AIRBNB.PROD.dim_hosts_cleansed\n    group by is_superhost\n\n)\n\nselect *\nfrom all_values\nwhere value_field not in (\n    't','f'\n)\n\n\n", "relation_name": "AIRBNB.DBT_TEST__AUDIT.accepted_values_dim_hosts_cleansed_is_superhost__t__f", "batch_results": null}, {"status": "success", "timing": [{"name": "compile", "started_at": "2026-06-22T20:20:17.362277Z", "completed_at": "2026-06-22T20:20:17.371553Z"}, {"name": "execute", "started_at": "2026-06-22T20:20:17.371759Z", "completed_at": "2026-06-22T20:20:17.371763Z"}], "thread_id": "Thread-5 (worker)", "execution_time": 0.011039257049560547, "adapter_response": {}, "message": null, "failures": null, "unique_id": "test.airbnb.not_null_dim_hosts_cleansed_host_id.de84c3da05", "compiled": true, "compiled_code": "\n    \n    \n\n\n\nselect *\nfrom AIRBNB.PROD.dim_hosts_cleansed\nwhere host_id is null\n\n\n", "relation_name": "AIRBNB.DBT_TEST__AUDIT.not_null_dim_hosts_cleansed_host_id", "batch_results": null}, {"status": "success", "timing": [{"name": "compile", "started_at": "2026-06-22T20:20:17.364449Z", "completed_at": "2026-06-22T20:20:17.372251Z"}, {"name": "execute", "started_at": "2026-06-22T20:20:17.372843Z", "completed_at": "2026-06-22T20:20:17.372846Z"}], "thread_id": "Thread-3 (worker)", "execution_time": 0.011852025985717773, "adapter_response": {}, "message": null, "failures": null, "unique_id": "test.airbnb.not_null_dim_hosts_cleansed_host_name.42386c5830", "compiled": true, "compiled_code": "\n    \n    \n\n\n\nselect *\nfrom AIRBNB.PROD.dim_hosts_cleansed\nwhere host_name is null\n\n\n", "relation_name": "AIRBNB.DBT_TEST__AUDIT.not_null_dim_hosts_cleansed_host_name", "batch_results": null}, {"status": "success", "timing": [{"name": "compile", "started_at": "2026-06-22T20:20:17.366840Z", "completed_at": "2026-06-22T20:20:17.372470Z"}, {"name": "execute", "started_at": "2026-06-22T20:20:17.373262Z", "completed_at": "2026-06-22T20:20:17.373266Z"}], "thread_id": "Thread-4 (worker)", "execution_time": 0.011927127838134766, "adapter_response": {}, "message": null, "failures": null, "unique_id": "test.airbnb.relationships_dim_listings_cleansed_host_id__host_id__ref_dim_hosts_cleansed_.b53b94b2ad", "compiled": true, "compiled_code": "\n    \n    \n\nwith child as (\n    select host_id as from_field\n    from AIRBNB.PROD.dim_listings_cleansed\n    where host_id is not null\n),\n\nparent as (\n    select host_id as to_field\n    from AIRBNB.PROD.dim_hosts_cleansed\n)\n\nselect\n    from_field\n\nfrom child\nleft join parent\n    on child.from_field = parent.to_field\n\nwhere parent.to_field is null\n\n\n", "relation_name": "AIRBNB.DBT_TEST__AUDIT.relationships_dim_listings_cle_05e2397b186a7b9306fc747b3cc4ef83", "batch_results": null}, {"status": "success", "timing": [{"name": "compile", "started_at": "2026-06-22T20:20:17.369504Z", "completed_at": "2026-06-22T20:20:17.373097Z"}, {"name": "execute", "started_at": "2026-06-22T20:20:17.373936Z", "completed_at": "2026-06-22T20:20:17.373938Z"}], "thread_id": "Thread-2 (worker)", "execution_time": 0.012068748474121094, "adapter_response": {}, "message": null, "failures": null, "unique_id": "test.airbnb.unique_dim_hosts_cleansed_host_id.d7e4771347", "compiled": true, "compiled_code": "\n    \n    \n\nselect\n    host_id as unique_field,\n    count(*) as n_records\n\nfrom AIRBNB.PROD.dim_hosts_cleansed\nwhere host_id is not null\ngroup by host_id\nhaving count(*) > 1\n\n\n", "relation_name": "AIRBNB.DBT_TEST__AUDIT.unique_dim_hosts_cleansed_host_id", "batch_results": null}, {"status": "success", "timing": [{"name": "compile", "started_at": "2026-06-22T20:20:17.374390Z", "completed_at": "2026-06-22T20:20:17.383404Z"}, {"name": "execute", "started_at": "2026-06-22T20:20:17.385931Z", "completed_at": "2026-06-22T20:20:17.385935Z"}], "thread_id": "Thread-5 (worker)", "execution_time": 0.013330221176147461, "adapter_response": {}, "message": null, "failures": null, "unique_id": "model.airbnb.mart_fullmoon_reviews", "compiled": true, "compiled_code": "\nWITH fct_reviews AS (\n    SELECT * FROM AIRBNB.PROD.fct_reviews\n),\nfull_moon_dates AS (\n    SELECT * FROM AIRBNB.PROD.seed_full_moon_dates\n)\n\nSELECT\n  r.*,\n  CASE\n    WHEN fm.full_moon_date IS NULL THEN 'not full moon'\n    ELSE 'full moon'\n  END AS is_full_moon\nFROM\n  fct_reviews\n  r\n  LEFT JOIN full_moon_dates\n  fm\n  ON (TO_DATE(r.review_date) = DATEADD(DAY, 1, fm.full_moon_date))", "relation_name": "AIRBNB.PROD.mart_fullmoon_reviews", "batch_results": null}, {"status": "success", "timing": [{"name": "compile", "started_at": "2026-06-22T20:20:17.377581Z", "completed_at": "2026-06-22T20:20:17.386655Z"}, {"name": "execute", "started_at": "2026-06-22T20:20:17.387194Z", "completed_at": "2026-06-22T20:20:17.387197Z"}], "thread_id": "Thread-3 (worker)", "execution_time": 0.010761260986328125, "adapter_response": {}, "message": null, "failures": null, "unique_id": "test.airbnb.consistent_created_at", "compiled": true, "compiled_code": "/* Create a singular test in tests/consistent_created_at.sql \nthat checks that there is no review date that is submitted before its listing was created: \nMake sure that every review_date in fct_reviews is more recent than \nthe associated created_at in dim_listings_cleansed. */\n\n\n\nWITH fct_reviews AS (\n    SELECT * FROM AIRBNB.PROD.fct_reviews\n),\ndim_listings_cleansed AS (\n    SELECT * FROM AIRBNB.PROD.dim_listings_cleansed\n)\nSELECT\n    cl.listing_id,\n    r.review_date,\n    cl.created_at\nFROM\n    dim_listings_cleansed cl\nJOIN fct_reviews  r\nON cl.listing_id = r.listing_id\nWHERE r.review_date < cl.created_at  \nLIMIT 10\n\n/* Important to remember when we check for condition we must retun \"bad\" records \n   only. This is way we esentialy must use reverse condition check. */", "relation_name": "AIRBNB.DBT_TEST__AUDIT.consistent_created_at", "batch_results": null}, {"status": "success", "timing": [{"name": "compile", "started_at": "2026-06-22T20:20:17.381265Z", "completed_at": "2026-06-22T20:20:17.386851Z"}, {"name": "execute", "started_at": "2026-06-22T20:20:17.387632Z", "completed_at": "2026-06-22T20:20:17.387635Z"}], "thread_id": "Thread-4 (worker)", "execution_time": 0.01081395149230957, "adapter_response": {}, "message": null, "failures": null, "unique_id": "test.airbnb.dbt_expectations_expect_column_max_to_be_between_dim_listings_w_hosts_price__5000.5218138b75", "compiled": true, "compiled_code": "\n\n\n\n\n    with grouped_expression as (\n    select\n        \n        \n    \n  \n( 1=1 and max(price) <= 5000\n)\n as expression\n\n\n    from AIRBNB.PROD.dim_listings_w_hosts\n    \n\n),\nvalidation_errors as (\n\n    select\n        *\n    from\n        grouped_expression\n    where\n        not(expression = true)\n\n)\n\nselect *\nfrom validation_errors\n\n\n\n\n\n", "relation_name": "AIRBNB.DBT_TEST__AUDIT.dbt_expectations_expect_column_c59e300e0dddb335c4211147100ac1c6", "batch_results": null}, {"status": "success", "timing": [{"name": "compile", "started_at": "2026-06-22T20:20:17.383612Z", "completed_at": "2026-06-22T20:20:17.387471Z"}, {"name": "execute", "started_at": "2026-06-22T20:20:17.394007Z", "completed_at": "2026-06-22T20:20:17.394011Z"}], "thread_id": "Thread-2 (worker)", "execution_time": 0.016822099685668945, "adapter_response": {}, "message": null, "failures": null, "unique_id": "test.airbnb.dbt_expectations_expect_column_quantile_values_to_be_between_dim_listings_w_hosts_price__500__50__0_99.71a0bfb970", "compiled": true, "compiled_code": "\n\n\n\n\n\n    with grouped_expression as (\n    select\n        \n        \n    \n  \n( 1=1 and percentile_cont(0.99) within group (order by price) >= 50 and percentile_cont(0.99) within group (order by price) <= 500\n)\n as expression\n\n\n    from AIRBNB.PROD.dim_listings_w_hosts\n    \n\n),\nvalidation_errors as (\n\n    select\n        *\n    from\n        grouped_expression\n    where\n        not(expression = true)\n\n)\n\nselect *\nfrom validation_errors\n\n\n\n\n\n", "relation_name": "AIRBNB.DBT_TEST__AUDIT.dbt_expectations_expect_column_39596d790161761077ff1592b68943f6", "batch_results": null}, {"status": "success", "timing": [{"name": "compile", "started_at": "2026-06-22T20:20:17.395136Z", "completed_at": "2026-06-22T20:20:17.469774Z"}, {"name": "execute", "started_at": "2026-06-22T20:20:17.470097Z", "completed_at": "2026-06-22T20:20:17.470102Z"}], "thread_id": "Thread-3 (worker)", "execution_time": 0.0756378173828125, "adapter_response": {}, "message": null, "failures": null, "unique_id": "test.airbnb.dbt_expectations_expect_table_row_count_to_equal_other_table_dim_listings_w_hosts_source_airbnb_listings_.637b6229da", "compiled": true, "compiled_code": "\n    with a as (\n        \n    select\n        \n        count(*) as expression\n    from\n        AIRBNB.PROD.dim_listings_w_hosts\n    \n\n    ),\n    b as (\n        \n    select\n        \n        count(*) * 1 as expression\n    from\n        AIRBNB.raw.raw_listings\n    \n\n    ),\n    final as (\n\n        select\n            \n            a.expression,\n            b.expression as compare_expression,\n            abs(coalesce(a.expression, 0) - coalesce(b.expression, 0)) as expression_difference,\n            abs(coalesce(a.expression, 0) - coalesce(b.expression, 0))/\n                nullif(a.expression * 1.0, 0) as expression_difference_percent\n        from\n        \n            a cross join b\n        \n    )\n    -- DEBUG:\n    -- select * from final\n    select\n        *\n    from final\n    where\n        \n        expression_difference > 0.0\n        \n", "relation_name": "AIRBNB.DBT_TEST__AUDIT.dbt_expectations_expect_table__fbda7436ebe2ffe341acf0622c76d629", "batch_results": null}, {"status": "success", "timing": [{"name": "compile", "started_at": "2026-06-22T20:20:17.387901Z", "completed_at": "2026-06-22T20:20:18.606976Z"}, {"name": "execute", "started_at": "2026-06-22T20:20:18.607479Z", "completed_at": "2026-06-22T20:20:18.607491Z"}], "thread_id": "Thread-5 (worker)", "execution_time": 1.2211427688598633, "adapter_response": {}, "message": null, "failures": null, "unique_id": "test.airbnb.dbt_expectations_expect_column_values_to_be_of_type_dim_listings_w_hosts_price__number.6e17061c8a", "compiled": true, "compiled_code": "with relation_columns as (\n\n        \n        select\n            cast('LISTING_ID' as TEXT) as relation_column,\n            cast('NUMBER' as TEXT) as relation_column_type\n        union all\n        \n        select\n            cast('LISTING_NAME' as TEXT) as relation_column,\n            cast('VARCHAR' as TEXT) as relation_column_type\n        union all\n        \n        select\n            cast('ROOM_TYPE' as TEXT) as relation_column,\n            cast('VARCHAR' as TEXT) as relation_column_type\n        union all\n        \n        select\n            cast('MINIMUM_NIGHTS' as TEXT) as relation_column,\n            cast('NUMBER' as TEXT) as relation_column_type\n        union all\n        \n        select\n            cast('PRICE' as TEXT) as relation_column,\n            cast('NUMBER' as TEXT) as relation_column_type\n        union all\n        \n        select\n            cast('HOST_ID' as TEXT) as relation_column,\n            cast('NUMBER' as TEXT) as relation_column_type\n        union all\n        \n        select\n            cast('HOST_NAME' as TEXT) as relation_column,\n            cast('VARCHAR' as TEXT) as relation_column_type\n        union all\n        \n        select\n            cast('HOST_IS_SUPERHOST' as TEXT) as relation_column,\n            cast('VARCHAR' as TEXT) as relation_column_type\n        union all\n        \n        select\n            cast('CREATED_AT' as TEXT) as relation_column,\n            cast('TIMESTAMP_NTZ' as TEXT) as relation_column_type\n        union all\n        \n        select\n            cast('UPDATED_AT' as TEXT) as relation_column,\n            cast('TIMESTAMP_NTZ' as TEXT) as relation_column_type\n        \n        \n    ),\n    test_data as (\n\n        select\n            *\n        from\n            relation_columns\n        where\n            relation_column = 'PRICE'\n            and\n            relation_column_type not in ('NUMBER')\n\n    )\n    select *\n    from test_data", "relation_name": "AIRBNB.DBT_TEST__AUDIT.dbt_expectations_expect_column_07e7a515218ef6e3a17e164c642c7d18", "batch_results": null}], "elapsed_time": 5.772471904754639, "args": {"project_dir": "/Users/ghg.vspahta/Projects/dbt-student-repo/airbnb", "printer_width": 80, "log_file_max_bytes": 10485760, "macro_debugging": false, "vars": {}, "log_level": "info", "output": "text", "cache_selected_only": false, "inject_ephemeral_ctes": true, "print": true, "log_format_file": "debug", "target_path": "target-prod", "which": "compile", "require_unique_project_resource_names": false, "invocation_command": "dbt compile --profiles-dir _prod_profiles --target prod --target-path target-prod", "require_yaml_configuration_for_mf_time_spines": false, "defer": false, "require_explicit_package_overrides_for_builtin_materializations": true, "send_anonymous_usage_stats": true, "skip_nodes_if_on_run_start_fails": false, "version_check": true, "use_colors_file": true, "require_ref_searches_node_package_before_root": false, "log_path": "/Users/ghg.vspahta/Projects/dbt-student-repo/airbnb/logs", "partial_parse": true, "require_all_warnings_handled_by_warn_error": false, "use_colors": true, "empty": false, "validate_macro_args": false, "require_batched_execution_for_custom_microbatch_strategy": false, "source_freshness_run_project_hooks": true, "require_generic_test_arguments_property": true, "show_resource_report": false, "static_parser": true, "warn_error_options": {"error": [], "warn": [], "silence": []}, "log_level_file": "debug", "show_all_deprecations": false, "target": "prod", "require_nested_cumulative_type_params": false, "upload_to_artifacts_ingest_api": false, "log_format": "default", "use_fast_test_edges": false, "introspect": true, "quiet": false, "strict_mode": false, "state_modified_compare_more_unrendered_values": false, "write_json": true, "require_resource_names_without_spaces": true, "state_modified_compare_vars": false, "partial_parse_file_diff": true, "indirect_selection": "eager", "favor_state": false, "populate_cache": true, "profiles_dir": "_prod_profiles", "exclude": [], "select": []}}